{
    "Ar36": {
        "error": 0.00024213401242243282,
        "error_type": "SEM",
        "filter_outliers_dict": {
            "filter_outliers": true,
            "iterations": 1,
            "std_devs": 3,
            "use_iqr_filtering": false,
            "use_standard_deviation_filtering": false
        },
        "fit": "Parabolic",
        "fn": 397,
        "include_baseline_error": true,
        "n": 400,
        "outlier_excluded": [
            0,
            123,
            263
        ],
        "reviewed": true,
        "user_excluded": [],
        "value": 0.01069015481825953
    },
    "Ar37": {
        "error": 0.002928565994823407,
        "error_type": "SEM",
        "filter_outliers_dict": {
            "filter_outliers": true,
            "iterations": 1,
            "std_devs": 3,
            "use_iqr_filtering": false,
            "use_standard_deviation_filtering": false
        },
        "fit": "Linear",
        "fn": 399,
        "include_baseline_error": true,
        "n": 400,
        "outlier_excluded": [
            10
        ],
        "reviewed": true,
        "user_excluded": [],
        "value": 0.3906927138773277
    },
    "Ar38": {
        "error": 0.0026961591821707234,
        "error_type": "SEM",
        "filter_outliers_dict": {
            "filter_outliers": true,
            "iterations": 1,
            "std_devs": 3,
            "use_iqr_filtering": false,
            "use_standard_deviation_filtering": false
        },
        "fit": "Linear",
        "fn": 397,
        "include_baseline_error": true,
        "n": 400,
        "outlier_excluded": [
            0,
            1,
            380
        ],
        "reviewed": true,
        "user_excluded": [],
        "value": 0.31597635916084393
    },
    "Ar39": {
        "error": 0.013174233249045922,
        "error_type": "SEM",
        "filter_outliers_dict": {
            "filter_outliers": true,
            "iterations": 1,
            "std_devs": 3,
            "use_iqr_filtering": false,
            "use_standard_deviation_filtering": false
        },
        "fit": "Parabolic",
        "fn": 400,
        "include_baseline_error": true,
        "n": 400,
        "outlier_excluded": [],
        "reviewed": true,
        "user_excluded": [],
        "value": 24.69803789220372
    },
    "Ar40": {
        "error": 0.01728059694820395,
        "error_type": "SEM",
        "filter_outliers_dict": {
            "filter_outliers": true,
            "iterations": 1,
            "std_devs": 3,
            "use_iqr_filtering": false,
            "use_standard_deviation_filtering": false
        },
        "fit": "Parabolic",
        "fn": 399,
        "include_baseline_error": true,
        "n": 400,
        "outlier_excluded": [
            361
        ],
        "reviewed": true,
        "user_excluded": [],
        "value": 106.12596862763309
    },
    "Ar41": {
        "error": 0.0029549513403849164,
        "error_type": "SEM",
        "filter_outliers_dict": {
            "filter_outliers": true,
            "iterations": 1,
            "std_devs": 2
        },
        "fit": "linear",
        "value": -0.4172722446053072
    }
}